excelproject/.DS_Store
excelproject/Testcases/.DS_Store
excelproject/Testcases/00239052590002_C382602015M_SGD_022022.pdf
excelproject/Testcases/00239052590002_C382602015M_SGD_022022.xlsx
excelproject/Testcases/1.pdf
excelproject/Testcases/1.xlsx
excelproject/Testcases/2211 bank statement Nov-22.pdf
excelproject/Testcases/2211 bank statement Nov-22.xlsx
excelproject/Testcases/sample.pdf
excelproject/Testcases/sample.xlsx
excelproject/__init__.py
excelproject/main.py
excelproject/resources/fonts/UbuntuMono-Regular.ttf
excelproject/startup.sh
excelproject/utils.py
excelproject-1.1.2.dist-info/LICENSE
excelproject-1.1.2.dist-info/METADATA
excelproject-1.1.2.dist-info/WHEEL
excelproject-1.1.2.dist-info/entry_points.txt
excelproject-1.1.2.dist-info/RECORD
